Metadata-Version: 2.1
Name: xfactor
Version: 0.4
Summary: Matplotlib magic header for easy switch between pgf and svg backends
Home-page: https://github.com/yhtang
Author: Yu-Hang Tang
Author-email: Tang.Maxin@gmail.com
License: All rights reserved
Platform: any
Classifier: Programming Language :: Python
